zibanu/django/template/__init__.py
zibanu/django/template/apps.py
zibanu/django/template/context_processors/__init__.py
zibanu/django/template/context_processors/full_static_uri.py
zibanu/django/template/context_processors/site.py
zibanu/django/template/templatetags/__init__.py
zibanu/django/template/templatetags/zb_tags/__init__.py
zibanu/django/template/templatetags/zb_tags/zb_concat.py
zibanu/django/template/templatetags/zb_tags/zb_divide.py
zibanu/django/template/templatetags/zb_tags/zb_multiply.py
zibanu/django/template/templatetags/zb_tags/zb_query_filter.py
zibanu/django/template/templatetags/zb_tags/zb_replace.py
zibanu/django/template/templatetags/zb_tags/zb_static_uri.py
zibanu/django/template/templatetags/zb_tags/zb_subtotal_dict.py
zibanu/django/template/templatetags/zb_tags/zb_sum_dict.py
zibanu_django_template-1.0.2.dist-info/licenses/LICENSE
zibanu_django_template-1.0.2.dist-info/METADATA
zibanu_django_template-1.0.2.dist-info/WHEEL
zibanu_django_template-1.0.2.dist-info/top_level.txt
zibanu_django_template-1.0.2.dist-info/RECORD
